[
    {
        "title": "Разработчик Python",
        "link": "https://hh.ru/vacancy/107347483",
        "salary": "Не указана",
        "description": "Описание отсутствует"
    },
    {
        "title": "Аналитик по стратегии",
        "link": "https://hh.ru/vacancy/107770018",
        "salary": "Не указана",
        "description": "Описание отсутствует"
    },
    {
        "title": "Педагог дополнительного образования в школах в Москве",
        "link": "https://hh.ru/vacancy/107772732",
        "salary": "Не указана",
        "description": "Описание отсутствует"
    },
    {
        "title": "Python - разработчик (async)",
        "link": "https://hh.ru/vacancy/107471332",
        "salary": "Не указана",
        "description": "Описание отсутствует"
    },
    {
        "title": "Data Scientist",
        "link": "https://hh.ru/vacancy/103980096",
        "salary": "Не указана",
        "description": "Описание отсутствует"
    },
    {
        "title": "Биоинформатик / Data-Engineer (Middle)",
        "link": "https://hh.ru/vacancy/107508920",
        "salary": "Не указана",
        "description": "Описание отсутствует"
    },
    {
        "title": "Python-developer / разработчик в it-hub(Хаб)",
        "link": "https://hh.ru/vacancy/106832145",
        "salary": "Не указана",
        "description": "Описание отсутствует"
    },
    {
        "title": "Специалист технической поддержки (First Line Support)",
        "link": "https://hh.ru/vacancy/107870665",
        "salary": "Не указана",
        "description": "Описание отсутствует"
    },
    {
        "title": "Computer Vision Engineer",
        "link": "https://hh.ru/vacancy/106446440",
        "salary": "Не указана",
        "description": "Описание отсутствует"
    },
    {
        "title": "Инженер в отдел внедрения L2-L3",
        "link": "https://hh.ru/vacancy/106883995",
        "salary": "Не указана",
        "description": "Описание отсутствует"
    },
    {
        "title": "Менеджер по продажам электротехнического оборудования (технико-коммерческий представитель)",
        "link": "https://hh.ru/vacancy/106541085",
        "salary": "Не указана",
        "description": "Описание отсутствует"
    },
    {
        "title": "Помощник руководителя проектов",
        "link": "https://hh.ru/vacancy/106785665",
        "salary": "Не указана",
        "description": "Описание отсутствует"
    },
    {
        "title": "Junior Python разработчик дата-платформы",
        "link": "https://hh.ru/vacancy/106803106",
        "salary": "Не указана",
        "description": "Описание отсутствует"
    },
    {
        "title": "Эксперт Риски на финансовых рынках (Junior Python Разработчик)",
        "link": "https://hh.ru/vacancy/107385382",
        "salary": "Не указана",
        "description": "Описание отсутствует"
    },
    {
        "title": "Team-lead/Senior Python developer",
        "link": "https://hh.ru/vacancy/107123723",
        "salary": "Не указана",
        "description": "Описание отсутствует"
    },
    {
        "title": "Начальник отдела актуарного анализа",
        "link": "https://hh.ru/vacancy/107753342",
        "salary": "Не указана",
        "description": "Описание отсутствует"
    },
    {
        "title": "Проектный аналитик",
        "link": "https://hh.ru/vacancy/105667322",
        "salary": "Не указана",
        "description": "Описание отсутствует"
    },
    {
        "title": "Python разработчик в финтех-гигант",
        "link": "https://hh.ru/vacancy/107807664",
        "salary": "Не указана",
        "description": "Описание отсутствует"
    },
    {
        "title": "Проектный аналитик",
        "link": "https://hh.ru/vacancy/107241109",
        "salary": "Не указана",
        "description": "Описание отсутствует"
    },
    {
        "title": "Руководитель разработки Full Stack (Java/React)",
        "link": "https://hh.ru/vacancy/106608049",
        "salary": "Не указана",
        "description": "Описание отсутствует"
    }
]